stablemotifs_setup.py
stablemotifs/__init__.py
stablemotifs/jupyter.py
stablemotifs/results.py
stablemotifs-1.0.dist-info/METADATA
stablemotifs-1.0.dist-info/WHEEL
stablemotifs-1.0.dist-info/top_level.txt
stablemotifs-1.0.dist-info/RECORD
