Metadata-Version: 2.1
Name: stablemotifs
Version: 1.0
Summary: Python interface to StableMotifs
Home-page: https://github.com/algorecell/pyStableMotifs
Author: Loïc Paulevé
Author-email: loic.pauleve@labri.fr
License: UNKNOWN
Keywords: computational systems biology
Platform: UNKNOWN
Classifier: Intended Audience :: Science/Research
Classifier: Topic :: Scientific/Engineering :: Bio-Informatics
Requires-Dist: colomoto-jupyter
Requires-Dist: algorecell-types
Requires-Dist: pandas
